top_hack/__init__.py
top_hack/cli.py
top_hack/top_hack.py
tophack-0.2.0.dist-info/AUTHORS.rst
tophack-0.2.0.dist-info/LICENSE
tophack-0.2.0.dist-info/METADATA
tophack-0.2.0.dist-info/WHEEL
tophack-0.2.0.dist-info/entry_points.txt
tophack-0.2.0.dist-info/top_level.txt
tophack-0.2.0.dist-info/RECORD
