Metadata-Version: 2.1
Name: tophack
Version: 0.2.0
Summary: Get top links from HN
Home-page: https://github.com/confuzeus/top_hack
Author: Josh Michael Karamuth
Author-email: michael@confuzeus.com
License: MIT license
Keywords: top_hack
Platform: UNKNOWN
Classifier: Development Status :: 2 - Pre-Alpha
Classifier: Intended Audience :: Developers
Classifier: License :: OSI Approved :: MIT License
Classifier: Natural Language :: English
Classifier: Programming Language :: Python :: 3
Classifier: Programming Language :: Python :: 3.6
Classifier: Programming Language :: Python :: 3.7
Classifier: Programming Language :: Python :: 3.8
Requires-Python: >=3.6
License-File: LICENSE
License-File: AUTHORS.rst
Requires-Dist: beautifulsoup4
Requires-Dist: requests
